security_agent_sdk/__init__.py
security_agent_sdk/exceptions.py
security_agent_sdk/validation.py
security_agent_sdk/models/__init__.py
security_agent_sdk/models/request.py
security_agent_sdk/models/response.py
security_agent_sdk-0.1.1.dist-info/METADATA
security_agent_sdk-0.1.1.dist-info/WHEEL
security_agent_sdk-0.1.1.dist-info/licenses/LICENSE
security_agent_sdk-0.1.1.dist-info/RECORD
