Metadata-Version: 2.4
Name: security-agent-sdk
Version: 0.1.1
Summary: Python SDK for Security Agent specifications (models and JSON Schemas)
Project-URL: Homepage, https://github.com/Logarithm-Labs/security-agent-sdk
Project-URL: Documentation, https://github.com/Logarithm-Labs/security-agent-sdk#readme
Project-URL: Repository, https://github.com/Logarithm-Labs/security-agent-sdk
Project-URL: Issues, https://github.com/Logarithm-Labs/security-agent-sdk/issues
Author-email: FullMetalHodler <fullmetalhodler@logarithm.fi>
License: MIT
License-File: LICENSE
Keywords: audit,blockchain,jsonschema,pydantic,sdk,security
Classifier: Intended Audience :: Developers
Classifier: License :: OSI Approved :: MIT License
Classifier: Operating System :: OS Independent
Classifier: Programming Language :: Python :: 3
Classifier: Programming Language :: Python :: 3.10
Classifier: Topic :: Security
Classifier: Typing :: Typed
Requires-Python: >=3.10
Requires-Dist: jsonschema>=4.0.0
Requires-Dist: pydantic>=2.5.0
Requires-Dist: yield-analysis-sdk
